{"judul":"Traversal Script of the Loser Group!","slug":"traversal-script-of-the-loser-group","tipe":"Manhua","released":"Desember 21, 2021","rating":"7","author":"伊澄 分子互动 [Add, ]小一","artist":"","status":"Ongoing","genre":["Action","Adventure","Comedy","Drama","Fantasy","Shounen"],"synopsis":"Mo Wang, Mint, dan Wang Anda adalah tiga makhluk abadi kecil yang sempurna di dunia ini. Mereka membantu tuan rumah mereka mengubah hidup mereka dengan melintasi melalui kelahiran kembali, untuk mendapatkan aspirasi dan perlahan-lahan meningkatkan.","thumbnail":"https://kiryuu02.com/wp-content/uploads/2021/12/tsl235234523-e1640081821656-299713-aEBfjzXi.jpg"}