{"judul":"Vanguard of Light","slug":"vanguard-of-light","tipe":"Manhua","released":"November 11, 2021","rating":"7","author":"语丶","artist":"","status":"Ongoing","genre":["Action","Drama","Fantasy","Sci-fi","Shounen","Tragedy"],"synopsis":"Apa yang dikenal sebagai kegagalan operasi militer rahasia terbesar dalam seratus tahun, sekali lagi mengungkap “perselisihan senjata kuno” antara benua Barat dan Timur! frustrasi dengan kejadian ini, Ye Kong pensiun dari tentara dan kembali ke kota untuk menghabiskan hari-harinya dalam kekacauan, tetapi karena garis keturunan yang unik di tubuhnya, ia terjebak di tengah badai peristiwa. Setelah kematian tragis saudaranya dan penghukuman kekasihnya keluar dari tentara, nasib apa yang menanti Ye Kong setelah semua ini …","thumbnail":"https://kiryuu02.com/wp-content/uploads/2021/11/vanguard-of-light-297756-IBWQBWZW.jpg"}