{"judul":"Rebirth of the Top Villain","slug":"rebirth-of-the-top-villain","tipe":"Manhua","released":"Maret 27, 2021","rating":"6.5","author":"云栖动漫","artist":"","status":"Ongoing","genre":["Fantasy","Martial Arts"],"synopsis":"Untuk pertama kalinya, Yan Zhaoge memiliki perlengkapan bos level penuh. Persimpangan kedua, sebelum perkembangan peradaban seni bela diri, seperti orang yang terbiasa memainkan mode neraka dan tiba-tiba terlempar ke mode sederhana. Jangan terlalu keren! Tapi apakah plot ini salah? Saya bukan protagonis? Tapi penjahat Gao Fushuai yang bersaing dengan protagonis?","thumbnail":"https://kiryuu02.com/wp-content/uploads/2021/03/rebirth-of-the-top-villain-721424-aa391HXg-225x300.jpg"}