{"judul":"I Conquered A Religion, And With It Came A Harem","slug":"i-conquered-a-religion-and-with-it-came-a-harem","tipe":"Manhua","released":"April 5, 2021","rating":"6.5","author":"Studio Liangzhizhu","artist":"","status":"Ongoing","genre":["Ecchi","Fantasy","Harem","Romance"],"synopsis":"Investor elit menyeberang ke dunia game untuk menjadi penguasa sekte sihir? Namun, dia tidak bisa menahan permohonan dari gadis penyihir itu dan memulai jalan untuk mendominasi dunia lain!","thumbnail":"https://kiryuu02.com/wp-content/uploads/2021/04/i-conquered-a-religion-and-with-it-came-a-harem-542141-ohNjGgx1-225x300.jpg"}