{"judul":"Jueshi Guzun","slug":"jueshi-guzun","tipe":"Manhua","released":"Oktober 24, 2021","rating":"4.7","author":"","artist":"","status":"Ongoing","genre":["Action","Adventure","Comedy","Fantasy"],"synopsis":"Apakah bencana direncanakan atau tiba-tiba? ataukah itu konspirasi, kabut itu berat … Kehidupan anak laki-laki secara bertahap berkembang. Dia ingin menjadi orang yang kuat, membayar harga, dan tidak bisa menjadi orang biasa lagi. Jalan menuju serangan balik dimulai. Lihat bagaimana anak-anak sampah menguasai dunia.","thumbnail":"https://kiryuu02.com/wp-content/uploads/2021/10/jueshi-guzun-893133-o5OMFLda-212x300.jpg"}