{"judul":"I Have Survived 999 Calamities","slug":"i-have-survived-999-calamities","tipe":"Manhua","released":"April 3, 2022","rating":"7.00","author":"阅文漫画","artist":"","status":"Ongoing","genre":["Action","Comedy","Drama","Fantasy","Martial Arts","Shounen"],"synopsis":"Zhen Hetu selalu berpikir bahwa dia adalah seorang transmigran yang tidak beruntung. Setelah berkultivasi selama sepuluh tahun, dia tetap berada di alam pemurnian qi yang rendah (8585520/????) dan tidak tahu kapan dia akan melakukan terobosan! Kesengsaraan surgawinya yang ke-999 sedang terjadi di atas kepalanya dan itu adalah jenis yang akan membuat para pengkultivasi terhebat sekalipun menggigil ketakutan! Baru setelah dia mengajak adik perempuannya untuk berpetualang, dia menyadari… bahwa dia terlalu kuat.","thumbnail":"https://kiryuu02.com/wp-content/uploads/2022/04/i-have-survived-999-calamities-838405-vsdmM59G-227x300.jpg"}