{"judul":"I Have a Blade That Can Cut Heaven and Earth","slug":"i-have-a-blade-that-can-cut-heaven-and-earth","tipe":"Manhua","released":"Desember 27, 2023","rating":"7.00","author":"为峰文化","artist":"","status":"Ongoing","genre":["Action","Drama","Fantasy","Shounen"],"synopsis":"Kaisar Surgawi Lin Dao, dalam usahanya memahami hati pedang tertinggi, menyebarkan kultivasinya untuk memulai yang baru. Namun, dia dikhianati oleh Wang Xian’er, yang menyebabkan perubahan takhta surgawi. Di ambang kematian, Lin Dao memahami hati pedang tertinggi. Jiwanya tertidur selama ribuan tahun sebelum terbangun dan merasuki murid Sekte Pedang Surgawi yang ditinggalkan. Secara kebetulan, murid yang ditinggalkan itu dikirim ke Sekte Pedang Ilahi sebagai kambing hitam. Lin Dao kemudian menggunakan Sekte Pedang Ilahi sebagai markasnya, dengan cermat mempersiapkan balas dendam terhadap Wang Xian’er. Selanjutnya, Lin Dao memusnahkan Sekte Pedang Surgawi, mengalahkan Aula Pemusnahan Jiwa, dan dengan paksa menyatukan tiga benua besar. Hal ini juga mengungkap dalang yang selalu berada di balik layar – Azure Cloud Sect, kekuatan terkuat yang diciptakan oleh Wang Xian’er. Konflik antara kedua kaisar pun dimulai.","thumbnail":"https://kiryuu02.com/wp-content/uploads/2023/12/i-have-a-blade-that-can-cut-heaven-and-earth-552391-sRgWbMcM-225x300.webp"}