{"judul":"Otherworldly Evil Monarch","slug":"otherworldly-evil-monarch","tipe":"Manhua","released":"April 1, 2021","rating":"6.1","author":"Fengling Tianxia","artist":"","status":"Ongoing","genre":["Action","Adventure","Harem"],"synopsis":"Jun Xie adalah pembunuh nomor satu di dunia modern. Keterampilan dan pengetahuannya di bidang pembunuhan tidak tertandingi, prestasinya belum pernah terjadi sebelumnya, reputasinya membuat takut seluruh dunia bawah. Namun, selama misi untuk mengambil harta karun mistis, sebuah kecelakaan terjadi … Dia sekarang adalah Jun Moxie, seorang pelacur tingkat super berusia enam belas tahun, pewaris tunggal keluarga Jun yang menurun. Sebuah keluarga pahlawan yang gagah berani, ditinggalkan dengan kakek tua, paman yang lumpuh, dan pesta pora sebagai pewaris tunggal! Menerima kritik dunia dan tatapan dingin dengan senyuman, perjalanan barunya dimulai! Hidupnya akan diukir oleh keinginannya sendiri! Bangkit ke atas! Raja Jahat Jun Xie!\r\n “Cangkir ini aku bersulang untuk mereka yang telah kubunuh di kehidupan sebelumnya. Maafkan aku, karena tidak ada kesempatan bagimu untuk membalas dendam. Meneguk!”\r\n “Cangkir ini saya bersulang untuk mereka yang hidupnya akan saya ambil dalam hidup baru saya. Maafkan aku, karena kamu ditakdirkan mati oleh tanganku. Bersulang!”","thumbnail":"https://kiryuu02.com/wp-content/uploads/2021/04/otherworldly-evil-monarch-477365-6tXBohzZ-200x300.jpg"}