{"judul":"The Hunter","slug":"the-hunter","tipe":"Manhua","released":"Maret 3, 2021","rating":"7","author":"Big Bear","artist":"","status":"Ongoing","genre":["Action","Adventure","Drama","Fantasy","Martial Arts","Seinen"],"synopsis":"Chen BeiMing pernah menjadi pemburu muda dan berbakat dari Aliansi Surgawi, sampai ia dikhianati dan dibunuh oleh The Five Lords. Dia akan dibangkitkan ke masa lalu sementara ingatannya masih utuh dan bersumpah bahwa dia akan membalas dendam pada orang-orang yang mengkhianatinya. Dengan bantuan sprite pertempurannya, dia pernah naik ke jalan untuk menjadi yang terkuat lagi …","thumbnail":"https://kiryuu02.com/wp-content/uploads/2021/03/the-hunter-713366-J4FBDvrS-225x300.png"}