{"judul":"I Build an Industrial Empire on the Magic Continent","slug":"i-build-an-industrial-empire-on-the-magic-continent","rating":"7.6","Status":"Ongoing","Type":"Manhua","Released":"2024","Author":"巴诺动漫","Artist":"巴诺动漫","Posted By":"Danzell","Posted On":"Oktober 27, 2024","Updated On":"Oktober 14, 2025","Views":"?","genre":["Adventure","Fantasy","Shounen"],"synopsis":"Berlatar belakang dunia fantasi bergaya abad pertengahan dunia ini dipenuhi dengan keajaiban dan petualangan di mana berbagai ras dan budaya hidup berdampingan Perkebunan bangsawan kastil kuno hutan misterius dan pegunungan yang berbahaya menjadi pemandangan utama dunia ini Di dunia ini protagonisnya adalah seorang bangsawan muda yang mewarisi wilayah dan kekayaan keluarganya tetapi menghadapi berbagai tantangan dan cobaan Berbekal dukungan dari sebuah sistem sang protagonis menggunakan revolusi industri untuk menantang benua magis dan akhirnya mendominasi seluruh negeri dominance.","thumbnail":"https://kiryuu02.com/wp-content/uploads/2024/10/buildcunetnoise-scalelevel3x2000000-767672-72u9rRVZ.png"}