{"judul":"The Strongest Involution System","slug":"the-strongest-involution-system","tipe":"Manhua","released":"Mei 11, 2022","rating":"7.00","author":"若鸿文化","artist":"","status":"Ongoing","genre":["Action","Drama","Fantasy","Martial Arts","Shounen"],"synopsis":"Chu Xingchen melakukan perjalanan ke dunia budidaya abadi. Dia pikir dia bisa bersantai dan pensiun, tetapi dia secara paksa terikat oleh sistem Dewa Bela Diri terkuat dan dipaksa involusi, membuka jalan bagi protagonis laki-laki menuju puncak","thumbnail":"https://kiryuu02.com/wp-content/uploads/2022/05/the-strongest-involution-system-235795-6QZrrB1o-225x300.webp"}