{"judul":"Everlasting God of Sword","slug":"everlasting-god-of-sword","tipe":"Manhua","released":"Maret 4, 2021","rating":"7.3","author":"Meng Bai","artist":"","status":"Ongoing","genre":["Action","Adventure","Fantasy","Martial Arts"],"synopsis":"Dia berdiri di puncak dunia. Melampaui segalanya sejak lahir dalam seni pedang. Tapi takdir telah membuatnya lumpuh beberapa saat sebelum mencapai puncak. Tapi ceritanya terus berlanjut dan legenda akan bangkit kembali…","thumbnail":"https://kiryuu02.com/wp-content/uploads/2021/03/everlasting-god-of-sword-780270-SGb2yczO-225x300.jpg"}