{"judul":"I Can’t Accompany The Second Generation Of Immortal","slug":"i-can-t-accompany-the-second-generation-of-immortal","tipe":"Manhua","released":"Mei 26, 2021","rating":"7","author":"优时文化","artist":"","status":"Ongoing","genre":["Adventure","Harem","Martial Arts"],"synopsis":"Qi Weiwei, seorang penggemar keuangan kecil yang menganggur setelah lulus, secara tidak sengaja mewarisi sebuah rumah halaman di kota kuno, dan yang menyertainya utang tiga juta. Saya tidak pernah menyangka bahwa halaman ini ternyata menjadi tempat singgah bagi para murid dunia abadi untuk datang ke dunia untuk melewati malapetaka! Sungguh tuan muda yang sangat dingin, tuan muda yang jahat … Karena kamu ingin makan dan tinggal bersamaku, maka semua pergi bekerja dan lunasi utangku!","thumbnail":"https://kiryuu02.com/wp-content/uploads/2021/05/i-cant-accompany-the-second-generation-of-immortal-897976-hFNzAnVQ-225x300.jpg"}