{"judul":"I Learn to Kill Gods in an Asylum","slug":"i-learn-to-kill-gods-in-an-asylum","tipe":"Manhua","released":"Juni 22, 2023","rating":"7.00","author":"","artist":"","status":"Ongoing","genre":["Action","Drama","Fantasy","Shounen"],"synopsis":"Pernahkah Anda berpikir bahwa di balik kota yang dipenuhi lampu neon, monster dari dongeng kuno bersemayam? Pernahkah Anda berpikir bahwa jauh di atas langit, di belakang bulan, berdiri Tuhan yang mengawasi dunia fana? Pernahkah Anda berpikir bahwa di kota abad ke-21 yang padat ini, ada manusia super yang menjadi agen Seraph? Dalam masyarakat yang diperintah oleh manusia ini, banyak keanehan mengintai di dalamnya. Mikaela sang Seraph, Hades Penguasa Neraka, Poseidon sang Dewa laut… kemana para Dewa Xia pergi? Di dunia milik “manusia” ini, “Makhluk mitos” harus dilenyapkan.","thumbnail":"https://kiryuu02.com/wp-content/uploads/2023/06/learn-to-kill-gods-in-an-asylum-585132-JYRm0siV-210x300.jpg"}