{"judul":"I Have Twin Girlfriends","slug":"i-have-twin-girlfriends","tipe":"Manhua","released":"Maret 18, 2021","rating":"7","author":"Tiānkōng shù màn gōngchǎng","artist":"","status":"Ongoing","genre":["Drama","Ecchi","Harem","Romance","Slice of Life"],"synopsis":"Namaku Zhou Xiang, aku punya pacar yang sudah bersamaku selama 4 tahun. Dia baru saja memberitahuku bahwa dia memiliki saudara kembar setelah begitu lamanya dia berbohong padaku!","thumbnail":"https://kiryuu02.com/wp-content/uploads/2021/03/i-have-twin-girlfriends-197206-dIsaJuQF-225x300.jpg"}