{"judul":"If I Don’t Die Soon, I Will Rule The Demon Realm","slug":"if-i-don-t-die-soon-i-will-rule-the-demon-realm","tipe":"Manhua","released":"Agustus 23, 2024","rating":"7.00","author":"阳光","artist":"","status":"Ongoing","genre":["Action","Comedy","Drama","Fantasy","Harem","Shounen"],"synopsis":"Ye Ning memperoleh “jari emas” melalui perjalanan, dan selama dia masih hidup, dia akan menjadi tak terkalahkan. Jadi dia mulai bertindak gila. Tapi… Permaisuri Da Zhou: “Ketika aku melihat kehidupan Ye Ning, jika dia mati, aku akan hidup sendirian.” Penguasa abadi dunia atas: “Dunia ini begitu acuh tak acuh, tapi Tuan Ye tidak pernah membenciku, aku akan berusaha sekuat mungkin untuk melindunginya.” Ratusan juta orang: “Setiap orang di dunia ini bisa kekurangan, tapi Tuan Ye adalah satu-satunya saint, hanya Ye Ning’er!” Ye Ning: Aku hampir tak terkalahkan, mengapa kalian tidak membiarkanku mati?","thumbnail":"https://kiryuu02.com/wp-content/uploads/2024/08/if-i-dont-die-soon-i-will-rule-the-demon-realm-979617-vPpRf1xf.webp"}