{"judul":"I Work Nine To Five In The Immortal Cultivation World","slug":"i-work-nine-to-five-in-the-immortal-cultivation-world","tipe":"Manhua","released":"Maret 19, 2023","rating":"7.00","author":"原著: 欢欢","artist":"","status":"Ongoing","genre":["Action","Comedy","Drama","Fantasy"],"synopsis":"Hua Qingyuan, meninggal secara tiba-tiba karena terlalu lelah bekerja dengan jadwal ‘996’. Namun, dia mendapati dirinya dipindahkan ke dunia fantasi dan menjadi murid dari Sekte Pedang Qingyun. Bertekad untuk tidak mengulangi kesalahan di masa lalunya, dia memutuskan untuk bekerja hanya 8 jam sehari dan tidak menghabiskan waktu setengah menit pun untuk berlatih kultivasi. Dia menjadi anomali di seluruh Sekte Pedang Qingyun, dengan malasnya berbaring di bawah pohon sementara yang lain berlatih siang dan malam. Dia menikmati hidupnya setelah bekerja, sementara yang lain bekerja tanpa lelah pada ilmu pedang mereka. Namun demikian, bakatnya yang hampir tidak normal dalam ilmu pedang membuatnya menjadi sosok yang tangguh. Dalam menghadapi permintaan dari gurunya, sesama murid, dan pemimpin sekte, serta serangan mendadak dari sekte iblis dan tantangan dari talenta muda lainnya, dia tetap bersikukuh: jangan menggangguku sampai tiba waktunya untuk bekerja!","thumbnail":"https://kiryuu02.com/wp-content/uploads/2023/03/i-work-nine-to-five-in-the-immortal-cultivation-world-803266-pATKCDu6.jpg"}