{"judul":"Blade and Expedition: Impervious Sword","slug":"blade-and-expedition-impervious-sword","tipe":"Manhua","released":"November 5, 2021","rating":"7","author":"AFK 剑与远征 [Add, ]莉莉丝游戏 [Add, ]","artist":"","status":"Ongoing","genre":["Action","Drama","Fantasy","Shounen"],"synopsis":"Di benua Isomia, perang antara Kekaisaran Ember dan Suku Darah Barbar akan segera dimulai. Thayne, yang sangat ingin menjadi pejuang yang kuat, pergi ke medan perang dengan pedangnya yang terkenal, Lotus, di mana ia bertemu Baden, seorang bangsawan yang juga seorang prajurit terlatih.\r\n Saingan yang ditakdirkan atau kawan? Ketika Thayne mulai memahami arti menjadi lebih kuat, konspirasi jahat yang tersembunyi di balik perang secara bertahap muncul …… The Glorious Empire, atau sisa yang terkubur dalam debu. Poros nasib, pada saat itu, berputar tiba-tiba.","thumbnail":"https://kiryuu02.com/wp-content/uploads/2021/11/blade-and-expedition-impervious-sword-709822-xYDkpaWY-225x300.jpeg"}