{"judul":"Jiang Ye","slug":"jiang-ye","tipe":"Manhua","released":"Desember 25, 2021","rating":"7.4","author":"Mao Ni","artist":"","status":"Ongoing","genre":["Action","Adventure","Comedy","Fantasy","Shounen"],"synopsis":"Sebuah adaptasi dari novel terkenal Jiang Ye! Salah satu prajurit biasa Dinasti Tang, seorang anak kecil pemberani, Ning Que, menerima perintah untuk mengawal kereta untuk meninggalkan Weicheng dan melangkah menuju Chang An!","thumbnail":"https://kiryuu02.com/wp-content/uploads/2021/12/13949-e1605411432979-716009-1vYcIzL8-203x300.webp"}